orq/__init__.py
orq/cli.py
orq/client.py
orq/config.py
orq/interactive.py
orq/utils.py
orq/commands/__init__.py
orq/commands/config_cmd.py
orq/commands/contacts.py
orq/commands/datasets.py
orq/commands/deployments.py
orq/commands/feedback.py
orq/commands/files.py
orq/commands/knowledge.py
orq/commands/prompts.py
orq_cli-0.1.4.dist-info/METADATA
orq_cli-0.1.4.dist-info/WHEEL
orq_cli-0.1.4.dist-info/entry_points.txt
orq_cli-0.1.4.dist-info/licenses/LICENSE
orq_cli-0.1.4.dist-info/RECORD
