Metadata-Version: 2.4
Name: orq-cli
Version: 0.1.4
Summary: Unofficial CLI tool for orq.ai LLM Ops platform
Project-URL: Homepage, https://github.com/nxtphase/orq-cli
Project-URL: Documentation, https://github.com/nxtphase/orq-cli#readme
Project-URL: Repository, https://github.com/nxtphase/orq-cli
Project-URL: Issues, https://github.com/nxtphase/orq-cli/issues
Author-email: Marco Kotrotsos <marco@nxtphase.io>
Maintainer-email: Marco Kotrotsos <marco@nxtphase.io>
License: MIT
License-File: LICENSE
Keywords: ai,cli,deployments,llm,llmops,orq,orq.ai,prompt-engineering
Classifier: Development Status :: 4 - Beta
Classifier: Environment :: Console
Classifier: Intended Audience :: Developers
Classifier: License :: OSI Approved :: MIT License
Classifier: Operating System :: OS Independent
Classifier: Programming Language :: Python :: 3
Classifier: Programming Language :: Python :: 3.9
Classifier: Programming Language :: Python :: 3.10
Classifier: Programming Language :: Python :: 3.11
Classifier: Programming Language :: Python :: 3.12
Classifier: Programming Language :: Python :: 3.13
Classifier: Topic :: Scientific/Engineering :: Artificial Intelligence
Classifier: Topic :: Software Development :: Libraries :: Python Modules
Classifier: Typing :: Typed
Requires-Python: >=3.9
Requires-Dist: orq-ai-sdk>=3.4.0
Requires-Dist: pyyaml>=6.0
Requires-Dist: questionary>=2.0.0
Requires-Dist: rich>=13.0.0
Requires-Dist: typer>=0.12.0
Provides-Extra: dev
Requires-Dist: build>=1.0.0; extra == 'dev'
Requires-Dist: pytest-cov>=4.0.0; extra == 'dev'
Requires-Dist: pytest>=8.0.0; extra == 'dev'
Requires-Dist: twine>=5.0.0; extra == 'dev'
